py_to_zip/__init__.py
py_to_zip/license.txt
py_to_zip/py_to_zip.py
py_to_zip-0.0.6.data/scripts/CZip.bat
py_to_zip-0.0.6.dist-info/METADATA
py_to_zip-0.0.6.dist-info/WHEEL
py_to_zip-0.0.6.dist-info/top_level.txt
py_to_zip-0.0.6.dist-info/RECORD
