Metadata-Version: 2.1
Name: py-to-zip
Version: 0.0.6
Summary: py-to-zip is a Python library that creates a zip file and a command file from your python code
Home-page: https://github.com/matan-h/czip
Author: matan h
Author-email: matan.honig2@gmail.com
License: MIT
Platform: UNKNOWN
Classifier: Programming Language :: Python :: 3
Classifier: License :: OSI Approved :: MIT License
Classifier: Operating System :: OS Independent
Requires-Python: >=3.0
